chatspec/__init__.py
chatspec/a2a.py
chatspec/markdown.py
chatspec/mcp.py
chatspec/mock.py
chatspec/params.py
chatspec/py.typed
chatspec/types.py
chatspec/utils.py
chatspec-0.0.17.dist-info/METADATA
chatspec-0.0.17.dist-info/WHEEL
chatspec-0.0.17.dist-info/licenses/LICENSE
chatspec-0.0.17.dist-info/RECORD
