Metadata-Version: 2.4
Name: chatspec
Version: 0.0.17
Summary: Simple types & utilities built for the OpenAI Chat Completions API specification.
Author-email: Hammad Saeed <hvmmad@gmail.com>
License:                                  Apache License
License-File: LICENSE
Requires-Python: >=3.10
Requires-Dist: cachetools>=5.5.1
Requires-Dist: docstring-parser>=0.16
Requires-Dist: pydantic>=2.10.6
Requires-Dist: typing-inspect>=0.9.0
Provides-Extra: client
Requires-Dist: instructor[litellm]; extra == 'client'
Requires-Dist: litellm; extra == 'client'
